qsarcons/__init__.py
qsarcons/cli.py
qsarcons/consensus.py
qsarcons/genopt.py
qsarcons/hopt.py
qsarcons/lazy.py
qsarcons/logging.py
qsarcons-1.1.1.dist-info/licenses/LICENSE
tests/conftest.py
tests/integration/test_workflow.py
qsarcons-1.1.1.dist-info/METADATA
qsarcons-1.1.1.dist-info/WHEEL
qsarcons-1.1.1.dist-info/top_level.txt
qsarcons-1.1.1.dist-info/RECORD
