Metadata-Version: 2.4
Name: qsarcons
Version: 1.1.1
Summary: Smart consensus QSAR
Author-email: Dmitry Zankov <dvzankov@gmail.com>
License: MIT
License-File: LICENSE
Requires-Dist: psutil
Requires-Dist: rdkit
Requires-Dist: molfeat
Requires-Dist: scikit-learn
Requires-Dist: xgboost
Requires-Dist: catboost
Requires-Dist: huggingface_hub
Requires-Dist: pytest
Dynamic: license-file
